accord_nlp/__init__.py
accord_nlp/data_augmentation.py
accord_nlp/information_extraction/__init__.py
accord_nlp/information_extraction/convertor.py
accord_nlp/information_extraction/ie_pipeline.py
accord_nlp/text_classification/__init__.py
accord_nlp/text_classification/config/__init__.py
accord_nlp/text_classification/config/model_args.py
accord_nlp/text_classification/config/utils.py
accord_nlp/text_classification/language_modelling/__init__.py
accord_nlp/text_classification/language_modelling/custom_models.py
accord_nlp/text_classification/language_modelling/lm_model.py
accord_nlp/text_classification/language_modelling/lm_utils.py
accord_nlp/text_classification/ner/__init__.py
accord_nlp/text_classification/ner/ner_model.py
accord_nlp/text_classification/ner/utils.py
accord_nlp/text_classification/relation_extraction/__init__.py
accord_nlp/text_classification/relation_extraction/re_model.py
accord_nlp/text_classification/relation_extraction/utils.py
accord_nlp/text_classification/relation_extraction/models/__init__.py
accord_nlp/text_classification/relation_extraction/models/albert_model.py
accord_nlp/text_classification/relation_extraction/models/bert_model.py
accord_nlp/text_classification/relation_extraction/models/roberta_model.py
accord_nlp-1.0.2.dist-info/licenses/LICENSE
accord_nlp-1.0.2.dist-info/METADATA
accord_nlp-1.0.2.dist-info/WHEEL
accord_nlp-1.0.2.dist-info/top_level.txt
accord_nlp-1.0.2.dist-info/RECORD
