Metadata-Version: 2.4
Name: accord_nlp
Version: 1.0.2
Summary: ACCORD-NLP: Transformer/language model-based information extraction from regulatory text
Home-page: https://github.com/Accord-Project/accord-nlp
Author: Hansi Hettiarachchi
Author-email: hansi.h.hettiarachchi@gmail.com
Keywords: NLP,NER,Relation Extraction,Information Extraction
Classifier: Intended Audience :: Science/Research
Classifier: License :: OSI Approved :: Apache Software License
Classifier: Programming Language :: Python :: 3
Classifier: Topic :: Scientific/Engineering :: Artificial Intelligence
Requires-Python: >=3.9
License-File: LICENSE
Requires-Dist: scikit-learn
Requires-Dist: statsmodels
Requires-Dist: matplotlib
Requires-Dist: openpyxl
Requires-Dist: nltk
Requires-Dist: transformers==4.40.2
Requires-Dist: seqeval
Requires-Dist: tensorboardX
Requires-Dist: wandb
Requires-Dist: sentencepiece
Requires-Dist: datasets
Requires-Dist: graphviz
Dynamic: author
Dynamic: author-email
Dynamic: classifier
Dynamic: description
Dynamic: description-content-type
Dynamic: home-page
Dynamic: keywords
Dynamic: license-file
Dynamic: requires-dist
Dynamic: requires-python
Dynamic: summary
